bocol/__init__.py
bocol-0.0.0.dist-info/METADATA
bocol-0.0.0.dist-info/WHEEL
bocol-0.0.0.dist-info/RECORD
